invenio_classifier/__init__.py
invenio_classifier/acronymer.py
invenio_classifier/api.py
invenio_classifier/config.py
invenio_classifier/engine.py
invenio_classifier/errors.py
invenio_classifier/extractor.py
invenio_classifier/find.py
invenio_classifier/keyworder.py
invenio_classifier/normalizer.py
invenio_classifier/reader.py
invenio_classifier/regexs.py
invenio_classifier/utils.py
invenio_classifier/version.py
invenio_classifier-1.3.10.dist-info/LICENSE
invenio_classifier-1.3.10.dist-info/METADATA
invenio_classifier-1.3.10.dist-info/WHEEL
invenio_classifier-1.3.10.dist-info/top_level.txt
invenio_classifier-1.3.10.dist-info/RECORD
