Metadata-Version: 2.1
Name: invenio-classifier
Version: 1.3.10
Summary: Invenio module for record classification.
Home-page: https://github.com/inveniosoftware-contrib/invenio-classifier
Author: CERN
Author-email: admin@inspirehep.net
License: GPLv2
Keywords: invenio keyword classification pdf
Platform: any
Classifier: Environment :: Web Environment
Classifier: Intended Audience :: Developers
Classifier: License :: OSI Approved :: GNU General Public License v2 (GPLv2)
Classifier: Operating System :: OS Independent
Classifier: Programming Language :: Python
Classifier: Topic :: Internet :: WWW/HTTP :: Dynamic Content
Classifier: Topic :: Software Development :: Libraries :: Python Modules
Classifier: Programming Language :: Python :: 2
Classifier: Programming Language :: Python :: 2.7
Classifier: Programming Language :: Python :: 3
Classifier: Programming Language :: Python :: 3.11
Classifier: Programming Language :: Python :: 3.12
Classifier: Programming Language :: Python :: 3.13
Classifier: Programming Language :: Python :: Implementation :: CPython
Classifier: Programming Language :: Python :: Implementation :: PyPy
Classifier: Development Status :: 5 - Production/Stable
License-File: LICENSE
Requires-Dist: rdflib==4.2.2
Requires-Dist: six>=1.10.0
Requires-Dist: requests>=2.9.1
Provides-Extra: all
Requires-Dist: coverage>=4.0; extra == "all"
Requires-Dist: pytest-cache>=1.0; extra == "all"
Requires-Dist: pytest-cov>=1.8.0; extra == "all"
Requires-Dist: pytest-pep8>=1.0.6; extra == "all"
Requires-Dist: pytest>=2.8.0; extra == "all"
Requires-Dist: mock>=3.0.5; extra == "all"
Provides-Extra: tests
Requires-Dist: coverage>=4.0; extra == "tests"
Requires-Dist: pytest-cache>=1.0; extra == "tests"
Requires-Dist: pytest-cov>=1.8.0; extra == "tests"
Requires-Dist: pytest-pep8>=1.0.6; extra == "tests"
Requires-Dist: pytest>=2.8.0; extra == "tests"
Requires-Dist: mock>=3.0.5; extra == "tests"
